kal/__main__.py
kal/application.py
kal/base/__init__.py
kal/base/json_obj.py
kal/commands/__init__.py
kal/commands/base.py
kal/commands/box.py
kal/commands/clone.py
kal/commands/docker.py
kal/commands/env.py
kal/commands/link.py
kal/commands/ocel.py
kal/commands/run.py
kal/commands/time.py
kal/helper.py
kal/initialize.py
kal/meta.py
kal/path.py
kal/runner.py
kal/utils/__init__.py
kal/utils/config.py
kal/utils/github.py
kal/utils/ocel.py
kal/utils/shell.py
kal/utils/storage.py
kal-0.6.0.dist-info/METADATA
kal-0.6.0.dist-info/WHEEL
kal-0.6.0.dist-info/entry_points.txt
kal-0.6.0.dist-info/RECORD
